.gitignore
LICENSE
MANIFEST.in
README.md
pyproject.toml
setup.py
calviacat/__init__.py
calviacat/_version.py
calviacat/catalog.py
calviacat/gaia.py
calviacat/panstarrs1.py
calviacat/refcat2.py
calviacat/skymapper.py
calviacat.egg-info/PKG-INFO
calviacat.egg-info/SOURCES.txt
calviacat.egg-info/dependency_links.txt
calviacat.egg-info/not-zip-safe
calviacat.egg-info/requires.txt
calviacat.egg-info/top_level.txt
calviacat/tests/__init__.py
calviacat/tests/test_gaia.py
calviacat/tests/data/dr2_1.vot
examples/lco-ps1-color-corrected.png
examples/lco-ps1-color-corrected.py
examples/lco-refcat2-color-corrected.png
examples/lco-refcat2-color-corrected.py
examples/lco-skymapper-constant.png
examples/lco-skymapper-constant.py