Metadata-Version: 2.1
Name: calviacat
Version: 1.3.1
Summary: Calibrate star photometry by comparison to a catalog.
Author-email: "Michael S. P. Kelley" <msk@astro.umd.edu>, Tim Lister <tlister@lco.global>
License: MIT
Project-URL: homepage, https://github.com/mkelley/calviacat
Keywords: astronomy,astrophysics,space,science
Requires-Python: >=3.8
License-File: LICENSE
Requires-Dist: astropy>=4.3
Requires-Dist: numpy
Requires-Dist: requests
Requires-Dist: astroquery>=0.4.5
